map_apply/__init__.py
map_apply/cli.py
map_apply/consts.py
map_apply/file_handler.py
map_apply/main.py
map_apply/scripts/__init__.py
map_apply/scripts/map_apply.py
map_apply-0.1.7.dist-info/entry_points.txt
map_apply-0.1.7.dist-info/WHEEL
map_apply-0.1.7.dist-info/METADATA
map_apply-0.1.7.dist-info/RECORD
