Metadata-Version: 2.1
Name: map-apply
Version: 0.1.7
Summary: Copies the input file and substitute one keyfield with another using 'map' file
License: MIT
Author: Smirnov Sergey
Requires-Python: >=3.8,<4.0
Classifier: License :: OSI Approved :: MIT License
Classifier: Programming Language :: Python :: 3
Classifier: Programming Language :: Python :: 3.8
Classifier: Programming Language :: Python :: 3.9
Requires-Dist: argparse (>=1.4.0,<2.0.0)
